unreal_mcp/__init__.py
unreal_mcp/server.py
unreal_mcp/tools/__init__.py
unreal_mcp/tools/blueprint_tools.py
unreal_mcp/tools/editor_tools.py
unreal_mcp/tools/node_tools.py
unreal_mcp/tools/project_tools.py
unreal_mcp/tools/umg_tools.py
unreal_mcp-0.1.1.dist-info/licenses/LICENSE
unreal_mcp-0.1.1.dist-info/METADATA
unreal_mcp-0.1.1.dist-info/WHEEL
unreal_mcp-0.1.1.dist-info/entry_points.txt
unreal_mcp-0.1.1.dist-info/top_level.txt
unreal_mcp-0.1.1.dist-info/RECORD
