Metadata-Version: 2.4
Name: unreal-mcp
Version: 0.1.1
Summary: Symbiote Labs' Unreal MCP Server: A server for Unreal Engine integration via the Model Context Protocol (MCP).
Author-email: Symbiote Labs <jonasz@symbiotelabs.ai>
Maintainer-email: Symbiote Labs <jonasz@symbiotelabs.ai>
License: MIT
Project-URL: Homepage, https://github.com/symbiote-labs/Symbiote_UE5
Project-URL: Documentation, https://github.com/symbiote-labs/Symbiote_UE5#readme
Project-URL: Repository, https://github.com/symbiote-labs/Symbiote_UE5.git
Project-URL: Bug Tracker, https://github.com/symbiote-labs/Symbiote_UE5/issues
Keywords: unreal-engine,mcp,model-context-protocol,automation,blueprint,umg,game-development
Classifier: Development Status :: 4 - Beta
Classifier: Intended Audience :: Developers
Classifier: License :: OSI Approved :: MIT License
Classifier: Operating System :: OS Independent
Classifier: Programming Language :: Python :: 3
Classifier: Programming Language :: Python :: 3.10
Classifier: Programming Language :: Python :: 3.11
Classifier: Programming Language :: Python :: 3.12
Classifier: Topic :: Games/Entertainment
Classifier: Topic :: Software Development :: Libraries :: Python Modules
Classifier: Topic :: System :: Networking
Requires-Python: >=3.10
License-File: LICENSE
Requires-Dist: mcp[cli]>=1.4.1
Requires-Dist: fastmcp>=0.2.0
Requires-Dist: uvicorn>=0.24.0
Requires-Dist: fastapi>=0.104.0
Requires-Dist: pydantic>=2.6.1
Requires-Dist: requests>=2.31.0
Provides-Extra: dev
Requires-Dist: pytest>=7.0.0; extra == "dev"
Requires-Dist: pytest-asyncio>=0.21.0; extra == "dev"
Requires-Dist: black>=23.0.0; extra == "dev"
Requires-Dist: isort>=5.12.0; extra == "dev"
Requires-Dist: flake8>=6.0.0; extra == "dev"
Requires-Dist: mypy>=1.5.0; extra == "dev"
Dynamic: license-file
